LICENSE
MANIFEST.in
README.rst
requirements.txt
setup.py
pwperformance/StaticVsInstanceMethod.py
pwperformance/__init__.py
pwperformance/client.py
pwperformance/hassAttrVsTry.py
pwperformance/main.py
pwperformance/loggers/__init__.py
pwperformance/loggers/influxdb.py
pwperformance/tests/__init__.py
pwperformance/tests/test_exportsteps.py
pwperformance/tests/test_influxhandler.py
pwperformance/tests/test_profiling_load.py
pwperformance/tests/test_set_performance.py
scipion_em_pwperformance.egg-info/PKG-INFO
scipion_em_pwperformance.egg-info/SOURCES.txt
scipion_em_pwperformance.egg-info/dependency_links.txt
scipion_em_pwperformance.egg-info/entry_points.txt
scipion_em_pwperformance.egg-info/requires.txt
scipion_em_pwperformance.egg-info/top_level.txt