Metadata-Version: 1.1
Name: scipion-em-pwperformance
Version: 0.0.5
Summary: Python module to provide performance analysis tools and storage of the metrics for a further comparison
Home-page: UNKNOWN
Author: Pablo Conesa
Author-email: pconesa@cnb.csic.es
License: UNKNOWN
Keywords: scipion cryoem imageprocessing scipion-3.0
Platform: UNKNOWN
Classifier: Development Status :: 3 - Alpha
Classifier: Intended Audience :: Science/Research
Classifier: License :: OSI Approved :: GNU General Public License v3 (GPLv3)
Classifier: Programming Language :: Python :: 3.6
Classifier: Programming Language :: Python :: 3.7
Classifier: Programming Language :: Python :: 3.8
Classifier: Topic :: Scientific/Engineering
